mgs_grf/__init__.py
mgs_grf/generalized_forest.py
mgs_grf/knn.py
mgs_grf/over_sampling.py
mgs_grf-0.0.1.dist-info/licenses/LICENSE
mgs_grf-0.0.1.dist-info/METADATA
mgs_grf-0.0.1.dist-info/WHEEL
mgs_grf-0.0.1.dist-info/top_level.txt
mgs_grf-0.0.1.dist-info/RECORD
