Metadata-Version: 2.4
Name: mgs_grf
Version: 0.0.1
Summary: MGS-GRF for imbalanced-mixed-tabular data
Author-email: Abdoulaye SAKHO <abdoulaye7020@gmail.com>, artefactory <abdoulaye.sakho@artefact.com>
License-Expression: MIT
Project-URL: Homepage, https://github.com/artefactory/mgs-grf
Project-URL: Repository, https://github.com/artefactory/mgs-grf
Keywords: mgs_grf,imbalanced-data,oversampling,tabular data,machine-learning
Classifier: Programming Language :: Python :: 3.9
Classifier: Programming Language :: Python :: 3.10
Classifier: Programming Language :: Python :: 3.11
Classifier: Programming Language :: Python :: 3.12
Classifier: Topic :: Scientific/Engineering :: Mathematics
Classifier: Topic :: Software Development
Requires-Python: <3.13,>=3.9
License-File: LICENSE
Requires-Dist: numpy>=1.26.4
Requires-Dist: scikit-learn>=1.5.1
Requires-Dist: imbalanced-learn>=0.12.3
Provides-Extra: dev
Requires-Dist: pytest>=8.4; extra == "dev"
Requires-Dist: pytest-cov>=7.0; extra == "dev"
Requires-Dist: pre-commit>=4.3; extra == "dev"
Requires-Dist: matplotlib>=3.7; extra == "dev"
Requires-Dist: pandas>=2.3; extra == "dev"
Requires-Dist: ucimlrepo>=0.0.7; extra == "dev"
Dynamic: license-file
